anetomy/__init__.py
anetomy/func_manager.py
anetomy/netvue.py
anetomy/network_renderer.py
anetomy/static/css/bootstrap.min.css
anetomy/static/css/docsearch.css
anetomy/static/css/header.css
anetomy/static/js/bootstrap.bundle.min.js
anetomy/static/js/color-modes.js
anetomy/templates/graph.html
anetomy-0.2.1.dist-info/licenses/LICENSE
anetomy-0.2.1.dist-info/METADATA
anetomy-0.2.1.dist-info/WHEEL
anetomy-0.2.1.dist-info/top_level.txt
anetomy-0.2.1.dist-info/RECORD
