Metadata-Version: 2.4
Name: anetomy
Version: 0.2.1
Summary: A neat instrument designed for visualizing neural networks.
Author-email: Seria <zzqsummerai@yeah.net>
License-File: LICENSE
Requires-Dist: graphviz
Requires-Dist: flask
Requires-Dist: torch>=1.0
Dynamic: license-file
